boosters/__init__.py
boosters/_boosters_rs.abi3.so
boosters/_boosters_rs.pyi
boosters/config.py
boosters/convert.py
boosters/dataset/__init__.py
boosters/dataset/builder.py
boosters/dataset/dataset.py
boosters/dataset/feature.py
boosters/metrics.py
boosters/model.py
boosters/objectives.py
boosters/persist/__init__.py
boosters/persist/schema.py
boosters/plotting.py
boosters/sklearn/__init__.py
boosters/sklearn/gbdt.py
boosters/sklearn/gblinear.py
boosters/types.py
boosters-0.1.0.dist-info/METADATA
boosters-0.1.0.dist-info/WHEEL
boosters-0.1.0.dist-info/RECORD
