Metadata-Version: 2.4
Name: boosters
Version: 0.1.0
Classifier: Development Status :: 2 - Pre-Alpha
Classifier: Intended Audience :: Developers
Classifier: Intended Audience :: Science/Research
Classifier: License :: OSI Approved :: MIT License
Classifier: Programming Language :: Python :: 3 :: Only
Classifier: Programming Language :: Python :: 3.12
Classifier: Programming Language :: Python :: 3.13
Classifier: Programming Language :: Python :: 3.14
Classifier: Programming Language :: Rust
Classifier: Topic :: Scientific/Engineering :: Artificial Intelligence
Requires-Dist: numpy>=1.26
Requires-Dist: pandas>=2 ; extra == 'pandas'
Requires-Dist: pydantic>=2 ; extra == 'schema'
Provides-Extra: pandas
Provides-Extra: schema
Summary: Fast gradient boosting library with native Rust core
Keywords: gbdt,gradient-boosting,lightgbm,machine-learning,xgboost
License: MIT
Requires-Python: >=3.12
